anonfaces/__init__.py
anonfaces/_version.py
anonfaces/anonfaces.py
anonfaces/centerface.onnx
anonfaces/centerface.py
anonfaces-1.0.0.dist-info/LICENSE
anonfaces-1.0.0.dist-info/METADATA
anonfaces-1.0.0.dist-info/WHEEL
anonfaces-1.0.0.dist-info/entry_points.txt
anonfaces-1.0.0.dist-info/top_level.txt
anonfaces-1.0.0.dist-info/RECORD
