Metadata-Version: 2.1
Name: anonfaces
Version: 1.0.0
Summary: Video anonymization by face detection
Home-page: https://github.com/StealUrKill/anonfaces
Author: Martin Drawitsch
Author-email: martin.drawitsch@gmail.com
Classifier: Programming Language :: Python :: 3
Classifier: License :: OSI Approved :: MIT License
Classifier: Operating System :: OS Independent
Requires-Python: >=3.6
License-File: LICENSE
Requires-Dist: imageio
Requires-Dist: imageio-ffmpeg
Requires-Dist: numpy
Requires-Dist: tqdm
Requires-Dist: scikit-image
Requires-Dist: opencv-python
Provides-Extra: gpu
Requires-Dist: onnxruntime-gpu ; extra == 'gpu'
